factorial_sum/__init__.py
factorial_sum/core.py
factorial_sum-0.1.2.dist-info/licenses/LICENSE
factorial_sum-0.1.2.dist-info/METADATA
factorial_sum-0.1.2.dist-info/WHEEL
factorial_sum-0.1.2.dist-info/top_level.txt
factorial_sum-0.1.2.dist-info/RECORD
