Metadata-Version: 2.4
Name: factorial-sum
Version: 0.1.2
Summary: Efficient computation of factorial sums using a novel recursive identity
Author-email: Abdelkrim Meziani <ramziabdelkrim@gmail.com>
License: MIT
Project-URL: Homepage, https://github.com/yourusername/factorial-sum
Project-URL: Documentation, https://pypi.org/project/factorial-sum/
Project-URL: Source, https://github.com/yourusername/factorial-sum
Keywords: factorial,mathematics,combinatorics,recursion,number-theory
Requires-Python: >=3.8
License-File: LICENSE
Dynamic: license-file
